stdopen/__init__.py
stdopen/_version.py
stdopen/stdopen.py
stdopen/example_data/__init__.py
stdopen/example_data/examples.py
stdopen/example_data/example_datasets/test_file.txt
stdopen/example_data/example_datasets/test_file.txt.gz
stdopen-0.2.3.dist-info/licenses/LICENCE.txt
stdopen-0.2.3.dist-info/METADATA
stdopen-0.2.3.dist-info/WHEEL
stdopen-0.2.3.dist-info/top_level.txt
stdopen-0.2.3.dist-info/RECORD
