Metadata-Version: 2.4
Name: stdopen
Version: 0.2.3
Summary: Streamlining file opening from files/stdin/stdout and write via temp
Author-email: Chris Finan <c.finan@ucl.ac.uk>
License-Expression: GPL-3.0-or-later
Project-URL: Homepage, https://cfinan.gitlab.io/stdopen/
Project-URL: Repository, https://gitlab.com/cfinan/stdopen
Classifier: Programming Language :: Python
Classifier: Programming Language :: Python :: 3
Classifier: Programming Language :: Python :: 3.9
Classifier: Programming Language :: Python :: 3.10
Classifier: Programming Language :: Python :: 3.11
Classifier: Programming Language :: Python :: 3.12
Classifier: Programming Language :: Python :: 3.13
Classifier: Programming Language :: Python :: Implementation :: CPython
Classifier: Programming Language :: Python :: Implementation :: PyPy
Requires-Python: <3.14,>=3.9
License-File: LICENCE.txt
Provides-Extra: dev
Requires-Dist: pytest; extra == "dev"
Requires-Dist: pytest-dependency; extra == "dev"
Requires-Dist: flake8; extra == "dev"
Requires-Dist: bump2version; extra == "dev"
Requires-Dist: build; extra == "dev"
Requires-Dist: twine; extra == "dev"
Dynamic: license-file
